salt_passbolt/__init__.py
passbolt_salt-1.0.3.dist-info/LICENSE
passbolt_salt-1.0.3.dist-info/METADATA
passbolt_salt-1.0.3.dist-info/WHEEL
passbolt_salt-1.0.3.dist-info/top_level.txt
passbolt_salt-1.0.3.dist-info/RECORD
