Metadata-Version: 2.1
Name: passbolt-salt
Version: 1.0.3
Summary: Integrate Passbolt into Saltstack to manage secrets in the infrastructure of your organization
Author-email: Sven Seeberg <sven.seeberg@netzbegruenung.de>, Alexander Bigga <alexander.bigga@verdigado.com>
Project-URL: Homepage, https://github.com/netzbegruenung/passbolt-salt
Project-URL: Issues, https://github.com/netzbegruenung/passbolt-salt/issues
Classifier: Programming Language :: Python :: 3
Classifier: License :: OSI Approved :: MIT License
Classifier: Operating System :: OS Independent
Requires-Python: >=3.8
License-File: LICENSE
Requires-Dist: passbolt-python-api
